tracfullblog/__init__.py
tracfullblog/admin.py
tracfullblog/api.py
tracfullblog/core.py
tracfullblog/db.py
tracfullblog/macros.py
tracfullblog/model.py
tracfullblog/spamfilter.py
tracfullblog/tags.py
tracfullblog/util.py
tracfullblog/web_ui.py
tracfullblog/htdocs/blog.png
tracfullblog/htdocs/css/fullblog.css
tracfullblog/templates/fullblog.rss
tracfullblog/templates/fullblog_admin.html
tracfullblog/templates/fullblog_archive.html
tracfullblog/templates/fullblog_delete.html
tracfullblog/templates/fullblog_edit.html
tracfullblog/templates/fullblog_macro_monthlist.html
tracfullblog/templates/fullblog_macro_post.html
tracfullblog/templates/fullblog_post.rss
tracfullblog/templates/fullblog_sidebar.html
tracfullblog/templates/fullblog_view.html
TracFullBlog-0.2.0.dist-info/METADATA
TracFullBlog-0.2.0.dist-info/WHEEL
TracFullBlog-0.2.0.dist-info/entry_points.txt
TracFullBlog-0.2.0.dist-info/top_level.txt
TracFullBlog-0.2.0.dist-info/RECORD
