Metadata-Version: 2.1
Name: TracFullBlog
Version: 0.2.0
Summary: Full-featured and self-contained Blog plugin for Trac.
Home-page: https://trac-hacks.org/wiki/FullBlogPlugin
Author: CodeResort.com = BV Network AS
Author-email: simon-code@bvnetwork.no
License: BSD
Keywords: trac blog
Platform: UNKNOWN
Classifier: Development Status :: 5 - Production/Stable
Classifier: Environment :: Plugins
Classifier: Environment :: Web Environment
Classifier: Framework :: Trac
Classifier: License :: OSI Approved :: BSD License
Classifier: Natural Language :: English
Classifier: Operating System :: OS Independent
Classifier: Programming Language :: Python :: 2
Classifier: Programming Language :: Python :: 2.7
Classifier: Programming Language :: Python :: 3
Provides-Extra: spamfilter
Requires-Dist: TracSpamFilter (>=1.4dev) ; extra == 'spamfilter'
Provides-Extra: tags
Requires-Dist: TracTags (>=0.11) ; extra == 'tags'
